[
  {
    "visible": true,
    "validSize": true,
    "x": 555,
    "y": 359,
    "width": 350,
    "height": 23,
    "left": 555,
    "top": 359,
    "right": 905,
    "bottom": 382,
    "minX": 555,
    "maxX": 905,
    "minY": 359,
    "maxY": 382,
    "xpath": "/HTML/BODY/DIV[4]/DIV/DIV/DIV/DIV[2]/DIV/DIV/DIV[3]",
    "positiveCoordinates": true
  },
  {
    "visible": true,
    "validSize": true,
    "x": 555,
    "y": 359,
    "width": 350,
    "height": 23,
    "left": 555,
    "top": 359,
    "right": 905,
    "bottom": 382,
    "minX": 555,
    "maxX": 905,
    "minY": 359,
    "maxY": 382,
    "xpath": "/HTML/BODY/DIV[4]/DIV/DIV/DIV/DIV[2]/DIV/DIV/DIV[3]/FORM",
    "positiveCoordinates": true
  },
  {
    "visible": true,
    "validSize": true,
    "x": 595,
    "y": 216,
    "width": 270,
    "height": 123,
    "left": 595,
    "top": 216,
    "right": 865,
    "bottom": 339,
    "minX": 595,
    "maxX": 865,
    "minY": 216,
    "maxY": 339,
    "xpath": "/HTML/BODY/DIV[4]/DIV/DIV/DIV/DIV[2]/DIV/DIV/DIV[2]",
    "positiveCoordinates": true
  },
  {
    "visible": true,
    "validSize": true,
    "x": 619,
    "y": 279,
    "width": 222,
    "height": 16,
    "left": 619,
    "top": 279,
    "right": 841,
    "bottom": 295,
    "minX": 619,
    "maxX": 841,
    "minY": 279,
    "maxY": 295,
    "xpath": "/HTML/BODY/DIV[4]/DIV/DIV/DIV/DIV[2]/DIV/DIV/DIV[2]/DIV",
    "positiveCoordinates": true
  },
  {
    "visible": true,
    "validSize": true,
    "x": 500,
    "y": 714,
    "width": 400,
    "height": 186,
    "left": 500,
    "top": 714,
    "right": 900,
    "bottom": 900,
    "minX": 500,
    "maxX": 900,
    "minY": 714,
    "maxY": 900,
    "xpath": "/HTML/BODY/DIV[4]/DIV[2]/DIV/DIV[2]/DIV[3]",
    "positiveCoordinates": true
  },
  {
    "visible": true,
    "validSize": true,
    "x": 500,
    "y": 714,
    "width": 400,
    "height": 186,
    "left": 500,
    "top": 714,
    "right": 900,
    "bottom": 900,
    "minX": 500,
    "maxX": 900,
    "minY": 714,
    "maxY": 900,
    "xpath": "/HTML/BODY/DIV[4]/DIV[2]/DIV/DIV[2]/DIV[3]/UL",
    "positiveCoordinates": true
  },
  {
    "visible": true,
    "validSize": true,
    "x": 500,
    "y": 714,
    "width": 370,
    "height": 62,
    "left": 500,
    "top": 714,
    "right": 870,
    "bottom": 776,
    "minX": 500,
    "maxX": 870,
    "minY": 714,
    "maxY": 776,
    "xpath": "/HTML/BODY/DIV[4]/DIV[2]/DIV/DIV[2]/DIV[3]/UL/LI",
    "positiveCoordinates": true
  },
  {
    "visible": true,
    "validSize": true,
    "x": 500,
    "y": 776,
    "width": 370,
    "height": 62,
    "left": 500,
    "top": 776,
    "right": 870,
    "bottom": 838,
    "minX": 500,
    "maxX": 870,
    "minY": 776,
    "maxY": 838,
    "xpath": "/HTML/BODY/DIV[4]/DIV[2]/DIV/DIV[2]/DIV[3]/UL/LI[2]",
    "positiveCoordinates": true
  },
  {
    "visible": true,
    "validSize": true,
    "x": 920,
    "y": 714,
    "width": 40,
    "height": 19,
    "left": 920,
    "top": 714,
    "right": 960,
    "bottom": 733,
    "minX": 920,
    "maxX": 960,
    "minY": 714,
    "maxY": 733,
    "xpath": "/HTML/BODY/DIV[4]/DIV[2]/DIV/DIV[2]/DIV[4]",
    "positiveCoordinates": true
  },
  {
    "visible": true,
    "validSize": true,
    "x": 500,
    "y": 838,
    "width": 370,
    "height": 62,
    "left": 500,
    "top": 838,
    "right": 870,
    "bottom": 900,
    "minX": 500,
    "maxX": 870,
    "minY": 838,
    "maxY": 900,
    "xpath": "/HTML/BODY/DIV[4]/DIV[2]/DIV/DIV[2]/DIV[3]/UL/LI[3]",
    "positiveCoordinates": true
  },
  {
    "visible": true,
    "validSize": true,
    "x": 500,
    "y": 103,
    "width": 460,
    "height": 332,
    "left": 500,
    "top": 103,
    "right": 960,
    "bottom": 435,
    "minX": 500,
    "maxX": 960,
    "minY": 103,
    "maxY": 435,
    "xpath": "/HTML/BODY/DIV[4]/DIV/DIV/DIV/DIV[2]",
    "positiveCoordinates": true
  },
  {
    "visible": true,
    "validSize": true,
    "x": 500,
    "y": 103,
    "width": 460,
    "height": 332,
    "left": 500,
    "top": 103,
    "right": 960,
    "bottom": 435,
    "minX": 500,
    "maxX": 960,
    "minY": 103,
    "maxY": 435,
    "xpath": "/HTML/BODY/DIV[4]/DIV/DIV/DIV/DIV[2]/DIV",
    "positiveCoordinates": true
  },
  {
    "visible": true,
    "validSize": true,
    "x": 500,
    "y": 122,
    "width": 460,
    "height": 31,
    "left": 500,
    "top": 122,
    "right": 960,
    "bottom": 153,
    "minX": 500,
    "maxX": 960,
    "minY": 122,
    "maxY": 153,
    "xpath": "/HTML/BODY/DIV[4]/DIV/DIV/DIV/DIV[2]/DIV/H1",
    "positiveCoordinates": true
  },
  {
    "visible": true,
    "validSize": true,
    "x": 500,
    "y": 153,
    "width": 460,
    "height": 23,
    "left": 500,
    "top": 153,
    "right": 960,
    "bottom": 176,
    "minX": 500,
    "maxX": 960,
    "minY": 153,
    "maxY": 176,
    "xpath": "/HTML/BODY/DIV[4]/DIV/DIV/DIV/DIV[2]/DIV/H3",
    "positiveCoordinates": true
  },
  {
    "visible": true,
    "validSize": true,
    "x": 500,
    "y": 416,
    "width": 460,
    "height": 19,
    "left": 500,
    "top": 416,
    "right": 960,
    "bottom": 435,
    "minX": 500,
    "maxX": 960,
    "minY": 416,
    "maxY": 435,
    "xpath": "/HTML/BODY/DIV[4]/DIV/DIV/DIV/DIV[2]/DIV/DIV[2]",
    "positiveCoordinates": true
  },
  {
    "visible": true,
    "validSize": true,
    "x": 555,
    "y": 196,
    "width": 350,
    "height": 200,
    "left": 555,
    "top": 196,
    "right": 905,
    "bottom": 396,
    "minX": 555,
    "maxX": 905,
    "minY": 196,
    "maxY": 396,
    "xpath": "/HTML/BODY/DIV[4]/DIV/DIV/DIV/DIV[2]/DIV/DIV",
    "positiveCoordinates": true
  },
  {
    "visible": true,
    "validSize": true,
    "x": 595.6875,
    "y": 359,
    "width": 202,
    "height": 23,
    "left": 595.6875,
    "top": 359,
    "right": 797.6875,
    "bottom": 382,
    "minX": 595.6875,
    "maxX": 797.6875,
    "minY": 359,
    "maxY": 382,
    "xpath": "/HTML/BODY/DIV[4]/DIV/DIV/DIV/DIV[2]/DIV/DIV/DIV[3]/FORM/INPUT",
    "positiveCoordinates": true
  },
  {
    "visible": true,
    "validSize": true,
    "x": 801.890625,
    "y": 360,
    "width": 62.40625,
    "height": 20,
    "left": 801.890625,
    "top": 360,
    "right": 864.296875,
    "bottom": 380,
    "minX": 801.890625,
    "maxX": 864.296875,
    "minY": 360,
    "maxY": 380,
    "xpath": "/HTML/BODY/DIV[4]/DIV/DIV/DIV/DIV[2]/DIV/DIV/DIV[3]/FORM/INPUT[2]",
    "positiveCoordinates": true
  },
  {
    "visible": true,
    "validSize": true,
    "x": 472.9375,
    "y": 0,
    "width": 94.25,
    "height": 50,
    "left": 472.9375,
    "top": 0,
    "right": 567.1875,
    "bottom": 50,
    "minX": 472.9375,
    "maxX": 567.1875,
    "minY": 0,
    "maxY": 50,
    "xpath": "/HTML/BODY/DIV[3]/DIV/DIV[2]/SPAN[2]",
    "positiveCoordinates": true
  },
  {
    "visible": true,
    "validSize": true,
    "x": 571.390625,
    "y": 0,
    "width": 90,
    "height": 50,
    "left": 571.390625,
    "top": 0,
    "right": 661.390625,
    "bottom": 50,
    "minX": 571.390625,
    "maxX": 661.390625,
    "minY": 0,
    "maxY": 50,
    "xpath": "/HTML/BODY/DIV[3]/DIV/DIV[2]/SPAN[3]",
    "positiveCoordinates": true
  },
  {
    "visible": true,
    "validSize": true,
    "x": 665.59375,
    "y": 0,
    "width": 90,
    "height": 50,
    "left": 665.59375,
    "top": 0,
    "right": 755.59375,
    "bottom": 50,
    "minX": 665.59375,
    "maxX": 755.59375,
    "minY": 0,
    "maxY": 50,
    "xpath": "/HTML/BODY/DIV[3]/DIV/DIV[2]/SPAN[4]",
    "positiveCoordinates": true
  },
  {
    "visible": true,
    "validSize": true,
    "x": 759.796875,
    "y": 0,
    "width": 103,
    "height": 40,
    "left": 759.796875,
    "top": 0,
    "right": 862.796875,
    "bottom": 40,
    "minX": 759.796875,
    "maxX": 862.796875,
    "minY": 0,
    "maxY": 40,
    "xpath": "/HTML/BODY/DIV[3]/DIV/DIV[2]/SPAN[5]",
    "positiveCoordinates": true
  },
  {
    "visible": true,
    "validSize": true,
    "x": 472.9375,
    "y": 0,
    "width": 94.25,
    "height": 50,
    "left": 472.9375,
    "top": 0,
    "right": 567.1875,
    "bottom": 50,
    "minX": 472.9375,
    "maxX": 567.1875,
    "minY": 0,
    "maxY": 50,
    "xpath": "/HTML/BODY/DIV[3]/DIV/DIV[2]/SPAN[2]/A",
    "positiveCoordinates": true
  },
  {
    "visible": true,
    "validSize": true,
    "x": 571.390625,
    "y": 0,
    "width": 90,
    "height": 50,
    "left": 571.390625,
    "top": 0,
    "right": 661.390625,
    "bottom": 50,
    "minX": 571.390625,
    "maxX": 661.390625,
    "minY": 0,
    "maxY": 50,
    "xpath": "/HTML/BODY/DIV[3]/DIV/DIV[2]/SPAN[3]/A",
    "positiveCoordinates": true
  },
  {
    "visible": true,
    "validSize": true,
    "x": 665.59375,
    "y": 0,
    "width": 90,
    "height": 50,
    "left": 665.59375,
    "top": 0,
    "right": 755.59375,
    "bottom": 50,
    "minX": 665.59375,
    "maxX": 755.59375,
    "minY": 0,
    "maxY": 50,
    "xpath": "/HTML/BODY/DIV[3]/DIV/DIV[2]/SPAN[4]/A",
    "positiveCoordinates": true
  },
  {
    "visible": true,
    "validSize": true,
    "x": 774.796875,
    "y": 11,
    "width": 88,
    "height": 29,
    "left": 774.796875,
    "top": 11,
    "right": 862.796875,
    "bottom": 40,
    "minX": 774.796875,
    "maxX": 862.796875,
    "minY": 11,
    "maxY": 40,
    "xpath": "/HTML/BODY/DIV[3]/DIV/DIV[2]/SPAN[5]/A",
    "positiveCoordinates": true
  },
  {
    "visible": true,
    "validSize": true,
    "x": 378.734375,
    "y": 0,
    "width": 90,
    "height": 50,
    "left": 378.734375,
    "top": 0,
    "right": 468.734375,
    "bottom": 50,
    "minX": 378.734375,
    "maxX": 468.734375,
    "minY": 0,
    "maxY": 50,
    "xpath": "/HTML/BODY/DIV[3]/DIV/DIV[2]/SPAN",
    "positiveCoordinates": true
  },
  {
    "visible": true,
    "validSize": true,
    "x": 378.734375,
    "y": 0,
    "width": 90,
    "height": 50,
    "left": 378.734375,
    "top": 0,
    "right": 468.734375,
    "bottom": 50,
    "minX": 378.734375,
    "maxX": 468.734375,
    "minY": 0,
    "maxY": 50,
    "xpath": "/HTML/BODY/DIV[3]/DIV/DIV[2]/SPAN/A",
    "positiveCoordinates": true
  },
  {
    "visible": true,
    "validSize": true,
    "x": 867,
    "y": 0,
    "width": 103,
    "height": 40,
    "left": 867,
    "top": 0,
    "right": 970,
    "bottom": 40,
    "minX": 867,
    "maxX": 970,
    "minY": 0,
    "maxY": 40,
    "xpath": "/HTML/BODY/DIV[3]/DIV/DIV[2]/SPAN[6]",
    "positiveCoordinates": true
  },
  {
    "visible": true,
    "validSize": true,
    "x": 882,
    "y": 11,
    "width": 88,
    "height": 29,
    "left": 882,
    "top": 11,
    "right": 970,
    "bottom": 40,
    "minX": 882,
    "maxX": 970,
    "minY": 11,
    "maxY": 40,
    "xpath": "/HTML/BODY/DIV[3]/DIV/DIV[2]/SPAN[6]/A",
    "positiveCoordinates": true
  },
  {
    "visible": true,
    "validSize": true,
    "x": 750,
    "y": 1357,
    "width": 200,
    "height": 18,
    "left": 750,
    "top": 1357,
    "right": 950,
    "bottom": 1375,
    "minX": 750,
    "maxX": 950,
    "minY": 1357,
    "maxY": 1375,
    "xpath": "/HTML/BODY/DIV[5]/DIV/DIV[4]/UL/LI[2]",
    "positiveCoordinates": true
  },
  {
    "visible": true,
    "validSize": true,
    "x": 750,
    "y": 1357,
    "width": 200,
    "height": 18,
    "left": 750,
    "top": 1357,
    "right": 950,
    "bottom": 1375,
    "minX": 750,
    "maxX": 950,
    "minY": 1357,
    "maxY": 1375,
    "xpath": "/HTML/BODY/DIV[5]/DIV/DIV[4]/UL/LI[2]/A",
    "positiveCoordinates": true
  },
  {
    "visible": true,
    "validSize": true,
    "x": 750,
    "y": 1387,
    "width": 200,
    "height": 18,
    "left": 750,
    "top": 1387,
    "right": 950,
    "bottom": 1405,
    "minX": 750,
    "maxX": 950,
    "minY": 1387,
    "maxY": 1405,
    "xpath": "/HTML/BODY/DIV[5]/DIV/DIV[4]/UL/LI[3]",
    "positiveCoordinates": true
  },
  {
    "visible": true,
    "validSize": true,
    "x": 750,
    "y": 1387,
    "width": 200,
    "height": 18,
    "left": 750,
    "top": 1387,
    "right": 950,
    "bottom": 1405,
    "minX": 750,
    "maxX": 950,
    "minY": 1387,
    "maxY": 1405,
    "xpath": "/HTML/BODY/DIV[5]/DIV/DIV[4]/UL/LI[3]/A",
    "positiveCoordinates": true
  },
  {
    "visible": true,
    "validSize": true,
    "x": 554.296875,
    "y": 1509,
    "width": 58,
    "height": 48,
    "left": 554.296875,
    "top": 1509,
    "right": 612.296875,
    "bottom": 1557,
    "minX": 554.296875,
    "maxX": 612.296875,
    "minY": 1509,
    "maxY": 1557,
    "xpath": "/HTML/BODY/DIV[6]/DIV/SPAN[4]",
    "positiveCoordinates": true
  },
  {
    "visible": true,
    "validSize": true,
    "x": 740,
    "y": 1273,
    "width": 220,
    "height": 154,
    "left": 740,
    "top": 1273,
    "right": 960,
    "bottom": 1427,
    "minX": 740,
    "maxX": 960,
    "minY": 1273,
    "maxY": 1427,
    "xpath": "/HTML/BODY/DIV[5]/DIV/DIV[4]",
    "positiveCoordinates": true
  },
  {
    "visible": true,
    "validSize": true,
    "x": 740,
    "y": 1273,
    "width": 220,
    "height": 40,
    "left": 740,
    "top": 1273,
    "right": 960,
    "bottom": 1313,
    "minX": 740,
    "maxX": 960,
    "minY": 1273,
    "maxY": 1313,
    "xpath": "/HTML/BODY/DIV[5]/DIV/DIV[4]/H4",
    "positiveCoordinates": true
  },
  {
    "visible": true,
    "validSize": true,
    "x": 740,
    "y": 1317,
    "width": 220,
    "height": 110,
    "left": 740,
    "top": 1317,
    "right": 960,
    "bottom": 1427,
    "minX": 740,
    "maxX": 960,
    "minY": 1317,
    "maxY": 1427,
    "xpath": "/HTML/BODY/DIV[5]/DIV/DIV[4]/UL",
    "positiveCoordinates": true
  },
  {
    "visible": true,
    "validSize": true,
    "x": 750,
    "y": 1327,
    "width": 200,
    "height": 18,
    "left": 750,
    "top": 1327,
    "right": 950,
    "bottom": 1345,
    "minX": 750,
    "maxX": 950,
    "minY": 1327,
    "maxY": 1345,
    "xpath": "/HTML/BODY/DIV[5]/DIV/DIV[4]/UL/LI",
    "positiveCoordinates": true
  },
  {
    "visible": true,
    "validSize": true,
    "x": 750,
    "y": 1327,
    "width": 200,
    "height": 18,
    "left": 750,
    "top": 1327,
    "right": 950,
    "bottom": 1345,
    "minX": 750,
    "maxX": 950,
    "minY": 1327,
    "maxY": 1345,
    "xpath": "/HTML/BODY/DIV[5]/DIV/DIV[4]/UL/LI/A",
    "positiveCoordinates": true
  },
  {
    "visible": true,
    "validSize": true,
    "x": 500,
    "y": 1273,
    "width": 220,
    "height": 214,
    "left": 500,
    "top": 1273,
    "right": 720,
    "bottom": 1487,
    "minX": 500,
    "maxX": 720,
    "minY": 1273,
    "maxY": 1487,
    "xpath": "/HTML/BODY/DIV[5]/DIV/DIV[3]",
    "positiveCoordinates": true
  },
  {
    "visible": true,
    "validSize": true,
    "x": 500,
    "y": 1273,
    "width": 220,
    "height": 40,
    "left": 500,
    "top": 1273,
    "right": 720,
    "bottom": 1313,
    "minX": 500,
    "maxX": 720,
    "minY": 1273,
    "maxY": 1313,
    "xpath": "/HTML/BODY/DIV[5]/DIV/DIV[3]/H4",
    "positiveCoordinates": true
  },
  {
    "visible": true,
    "validSize": true,
    "x": 500,
    "y": 1317,
    "width": 220,
    "height": 170,
    "left": 500,
    "top": 1317,
    "right": 720,
    "bottom": 1487,
    "minX": 500,
    "maxX": 720,
    "minY": 1317,
    "maxY": 1487,
    "xpath": "/HTML/BODY/DIV[5]/DIV/DIV[3]/UL",
    "positiveCoordinates": true
  },
  {
    "visible": true,
    "validSize": true,
    "x": 510,
    "y": 1327,
    "width": 200,
    "height": 18,
    "left": 510,
    "top": 1327,
    "right": 710,
    "bottom": 1345,
    "minX": 510,
    "maxX": 710,
    "minY": 1327,
    "maxY": 1345,
    "xpath": "/HTML/BODY/DIV[5]/DIV/DIV[3]/UL/LI",
    "positiveCoordinates": true
  },
  {
    "visible": true,
    "validSize": true,
    "x": 510,
    "y": 1357,
    "width": 200,
    "height": 18,
    "left": 510,
    "top": 1357,
    "right": 710,
    "bottom": 1375,
    "minX": 510,
    "maxX": 710,
    "minY": 1357,
    "maxY": 1375,
    "xpath": "/HTML/BODY/DIV[5]/DIV/DIV[3]/UL/LI[2]",
    "positiveCoordinates": true
  },
  {
    "visible": true,
    "validSize": true,
    "x": 510,
    "y": 1387,
    "width": 200,
    "height": 18,
    "left": 510,
    "top": 1387,
    "right": 710,
    "bottom": 1405,
    "minX": 510,
    "maxX": 710,
    "minY": 1387,
    "maxY": 1405,
    "xpath": "/HTML/BODY/DIV[5]/DIV/DIV[3]/UL/LI[3]",
    "positiveCoordinates": true
  },
  {
    "visible": true,
    "validSize": true,
    "x": 510,
    "y": 1327,
    "width": 200,
    "height": 18,
    "left": 510,
    "top": 1327,
    "right": 710,
    "bottom": 1345,
    "minX": 510,
    "maxX": 710,
    "minY": 1327,
    "maxY": 1345,
    "xpath": "/HTML/BODY/DIV[5]/DIV/DIV[3]/UL/LI/A",
    "positiveCoordinates": true
  },
  {
    "visible": true,
    "validSize": true,
    "x": 510,
    "y": 1357,
    "width": 200,
    "height": 18,
    "left": 510,
    "top": 1357,
    "right": 710,
    "bottom": 1375,
    "minX": 510,
    "maxX": 710,
    "minY": 1357,
    "maxY": 1375,
    "xpath": "/HTML/BODY/DIV[5]/DIV/DIV[3]/UL/LI[2]/A",
    "positiveCoordinates": true
  },
  {
    "visible": true,
    "validSize": true,
    "x": 510,
    "y": 1387,
    "width": 200,
    "height": 18,
    "left": 510,
    "top": 1387,
    "right": 710,
    "bottom": 1405,
    "minX": 510,
    "maxX": 710,
    "minY": 1387,
    "maxY": 1405,
    "xpath": "/HTML/BODY/DIV[5]/DIV/DIV[3]/UL/LI[3]/A",
    "positiveCoordinates": true
  },
  {
    "visible": true,
    "validSize": true,
    "x": 500,
    "y": 1062,
    "width": 220,
    "height": 72,
    "left": 500,
    "top": 1062,
    "right": 720,
    "bottom": 1134,
    "minX": 500,
    "maxX": 720,
    "minY": 1062,
    "maxY": 1134,
    "xpath": "/HTML/BODY/DIV[4]/DIV[3]/DIV/DIV[2]/DIV[3]",
    "positiveCoordinates": true
  },
  {
    "visible": true,
    "validSize": true,
    "x": 500,
    "y": 1062,
    "width": 220,
    "height": 72,
    "left": 500,
    "top": 1062,
    "right": 720,
    "bottom": 1134,
    "minX": 500,
    "maxX": 720,
    "minY": 1062,
    "maxY": 1134,
    "xpath": "/HTML/BODY/DIV[4]/DIV[3]/DIV/DIV[2]/DIV[3]/DIV",
    "positiveCoordinates": true
  },
  {
    "visible": true,
    "validSize": true,
    "x": 740,
    "y": 1062,
    "width": 220,
    "height": 81,
    "left": 740,
    "top": 1062,
    "right": 960,
    "bottom": 1143,
    "minX": 740,
    "maxX": 960,
    "minY": 1062,
    "maxY": 1143,
    "xpath": "/HTML/BODY/DIV[4]/DIV[3]/DIV/DIV[2]/DIV[4]",
    "positiveCoordinates": true
  },
  {
    "visible": true,
    "validSize": true,
    "x": 740,
    "y": 1062,
    "width": 220,
    "height": 81,
    "left": 740,
    "top": 1062,
    "right": 960,
    "bottom": 1143,
    "minX": 740,
    "maxX": 960,
    "minY": 1062,
    "maxY": 1143,
    "xpath": "/HTML/BODY/DIV[4]/DIV[3]/DIV/DIV[2]/DIV[4]/DIV",
    "positiveCoordinates": true
  },
  {
    "visible": true,
    "validSize": true,
    "x": 500,
    "y": 1103,
    "width": 1,
    "height": 1,
    "left": 500,
    "top": 1103,
    "right": 501,
    "bottom": 1104,
    "minX": 500,
    "maxX": 501,
    "minY": 1103,
    "maxY": 1104,
    "xpath": "/HTML/BODY/DIV[4]/DIV/DIV/DIV/DIV[2]/DIV/DIV/IFRAME",
    "positiveCoordinates": true
  },
  {
    "visible": true,
    "validSize": true,
    "x": 510,
    "y": 1417,
    "width": 200,
    "height": 18,
    "left": 510,
    "top": 1417,
    "right": 710,
    "bottom": 1435,
    "minX": 510,
    "maxX": 710,
    "minY": 1417,
    "maxY": 1435,
    "xpath": "/HTML/BODY/DIV[5]/DIV/DIV[3]/UL/LI[4]",
    "positiveCoordinates": true
  },
  {
    "visible": true,
    "validSize": true,
    "x": 510,
    "y": 1447,
    "width": 200,
    "height": 18,
    "left": 510,
    "top": 1447,
    "right": 710,
    "bottom": 1465,
    "minX": 510,
    "maxX": 710,
    "minY": 1447,
    "maxY": 1465,
    "xpath": "/HTML/BODY/DIV[5]/DIV/DIV[3]/UL/LI[5]",
    "positiveCoordinates": true
  },
  {
    "visible": true,
    "validSize": true,
    "x": 429.890625,
    "y": 1509,
    "width": 58,
    "height": 48,
    "left": 429.890625,
    "top": 1509,
    "right": 487.890625,
    "bottom": 1557,
    "minX": 429.890625,
    "maxX": 487.890625,
    "minY": 1509,
    "maxY": 1557,
    "xpath": "/HTML/BODY/DIV[6]/DIV/SPAN[2]",
    "positiveCoordinates": true
  },
  {
    "visible": true,
    "validSize": true,
    "x": 492.09375,
    "y": 1509,
    "width": 58,
    "height": 48,
    "left": 492.09375,
    "top": 1509,
    "right": 550.09375,
    "bottom": 1557,
    "minX": 492.09375,
    "maxX": 550.09375,
    "minY": 1509,
    "maxY": 1557,
    "xpath": "/HTML/BODY/DIV[6]/DIV/SPAN[3]",
    "positiveCoordinates": true
  },
  {
    "visible": true,
    "validSize": true,
    "x": 510,
    "y": 1417,
    "width": 200,
    "height": 18,
    "left": 510,
    "top": 1417,
    "right": 710,
    "bottom": 1435,
    "minX": 510,
    "maxX": 710,
    "minY": 1417,
    "maxY": 1435,
    "xpath": "/HTML/BODY/DIV[5]/DIV/DIV[3]/UL/LI[4]/A",
    "positiveCoordinates": true
  },
  {
    "visible": true,
    "validSize": true,
    "x": 510,
    "y": 1447,
    "width": 200,
    "height": 18,
    "left": 510,
    "top": 1447,
    "right": 710,
    "bottom": 1465,
    "minX": 510,
    "maxX": 710,
    "minY": 1447,
    "maxY": 1465,
    "xpath": "/HTML/BODY/DIV[5]/DIV/DIV[3]/UL/LI[5]/A",
    "positiveCoordinates": true
  },
  {
    "visible": true,
    "validSize": true,
    "x": 270,
    "y": 1327,
    "width": 200,
    "height": 18,
    "left": 270,
    "top": 1327,
    "right": 470,
    "bottom": 1345,
    "minX": 270,
    "maxX": 470,
    "minY": 1327,
    "maxY": 1345,
    "xpath": "/HTML/BODY/DIV[5]/DIV/DIV[2]/UL/LI",
    "positiveCoordinates": true
  },
  {
    "visible": true,
    "validSize": true,
    "x": 270,
    "y": 1327,
    "width": 200,
    "height": 18,
    "left": 270,
    "top": 1327,
    "right": 470,
    "bottom": 1345,
    "minX": 270,
    "maxX": 470,
    "minY": 1327,
    "maxY": 1345,
    "xpath": "/HTML/BODY/DIV[5]/DIV/DIV[2]/UL/LI/A",
    "positiveCoordinates": true
  },
  {
    "visible": true,
    "validSize": true,
    "x": 270,
    "y": 1357,
    "width": 200,
    "height": 36,
    "left": 270,
    "top": 1357,
    "right": 470,
    "bottom": 1393,
    "minX": 270,
    "maxX": 470,
    "minY": 1357,
    "maxY": 1393,
    "xpath": "/HTML/BODY/DIV[5]/DIV/DIV[2]/UL/LI[2]",
    "positiveCoordinates": true
  },
  {
    "visible": true,
    "validSize": true,
    "x": 270,
    "y": 1405,
    "width": 200,
    "height": 36,
    "left": 270,
    "top": 1405,
    "right": 470,
    "bottom": 1441,
    "minX": 270,
    "maxX": 470,
    "minY": 1405,
    "maxY": 1441,
    "xpath": "/HTML/BODY/DIV[5]/DIV/DIV[2]/UL/LI[3]",
    "positiveCoordinates": true
  },
  {
    "visible": true,
    "validSize": true,
    "x": 270,
    "y": 1357,
    "width": 200,
    "height": 36,
    "left": 270,
    "top": 1357,
    "right": 470,
    "bottom": 1393,
    "minX": 270,
    "maxX": 470,
    "minY": 1357,
    "maxY": 1393,
    "xpath": "/HTML/BODY/DIV[5]/DIV/DIV[2]/UL/LI[2]/A",
    "positiveCoordinates": true
  },
  {
    "visible": true,
    "validSize": true,
    "x": 270,
    "y": 1405,
    "width": 200,
    "height": 36,
    "left": 270,
    "top": 1405,
    "right": 470,
    "bottom": 1441,
    "minX": 270,
    "maxX": 470,
    "minY": 1405,
    "maxY": 1441,
    "xpath": "/HTML/BODY/DIV[5]/DIV/DIV[2]/UL/LI[3]/A",
    "positiveCoordinates": true
  },
  {
    "visible": true,
    "validSize": true,
    "x": 30,
    "y": 1357,
    "width": 200,
    "height": 18,
    "left": 30,
    "top": 1357,
    "right": 230,
    "bottom": 1375,
    "minX": 30,
    "maxX": 230,
    "minY": 1357,
    "maxY": 1375,
    "xpath": "/HTML/BODY/DIV[5]/DIV/DIV/UL/LI[2]",
    "positiveCoordinates": true
  },
  {
    "visible": true,
    "validSize": true,
    "x": 30,
    "y": 1387,
    "width": 200,
    "height": 18,
    "left": 30,
    "top": 1387,
    "right": 230,
    "bottom": 1405,
    "minX": 30,
    "maxX": 230,
    "minY": 1387,
    "maxY": 1405,
    "xpath": "/HTML/BODY/DIV[5]/DIV/DIV/UL/LI[3]",
    "positiveCoordinates": true
  },
  {
    "visible": true,
    "validSize": true,
    "x": 30,
    "y": 1417,
    "width": 200,
    "height": 18,
    "left": 30,
    "top": 1417,
    "right": 230,
    "bottom": 1435,
    "minX": 30,
    "maxX": 230,
    "minY": 1417,
    "maxY": 1435,
    "xpath": "/HTML/BODY/DIV[5]/DIV/DIV/UL/LI[4]",
    "positiveCoordinates": true
  },
  {
    "visible": true,
    "validSize": true,
    "x": 260,
    "y": 1273,
    "width": 220,
    "height": 190,
    "left": 260,
    "top": 1273,
    "right": 480,
    "bottom": 1463,
    "minX": 260,
    "maxX": 480,
    "minY": 1273,
    "maxY": 1463,
    "xpath": "/HTML/BODY/DIV[5]/DIV/DIV[2]",
    "positiveCoordinates": true
  },
  {
    "visible": true,
    "validSize": true,
    "x": 260,
    "y": 1273,
    "width": 220,
    "height": 40,
    "left": 260,
    "top": 1273,
    "right": 480,
    "bottom": 1313,
    "minX": 260,
    "maxX": 480,
    "minY": 1273,
    "maxY": 1313,
    "xpath": "/HTML/BODY/DIV[5]/DIV/DIV[2]/H4",
    "positiveCoordinates": true
  },
  {
    "visible": true,
    "validSize": true,
    "x": 260,
    "y": 1317,
    "width": 220,
    "height": 146,
    "left": 260,
    "top": 1317,
    "right": 480,
    "bottom": 1463,
    "minX": 260,
    "maxX": 480,
    "minY": 1317,
    "maxY": 1463,
    "xpath": "/HTML/BODY/DIV[5]/DIV/DIV[2]/UL",
    "positiveCoordinates": true
  },
  {
    "visible": true,
    "validSize": true,
    "x": 20,
    "y": 1273,
    "width": 220,
    "height": 184,
    "left": 20,
    "top": 1273,
    "right": 240,
    "bottom": 1457,
    "minX": 20,
    "maxX": 240,
    "minY": 1273,
    "maxY": 1457,
    "xpath": "/HTML/BODY/DIV[5]/DIV/DIV",
    "positiveCoordinates": true
  },
  {
    "visible": true,
    "validSize": true,
    "x": 20,
    "y": 1273,
    "width": 220,
    "height": 40,
    "left": 20,
    "top": 1273,
    "right": 240,
    "bottom": 1313,
    "minX": 20,
    "maxX": 240,
    "minY": 1273,
    "maxY": 1313,
    "xpath": "/HTML/BODY/DIV[5]/DIV/DIV/H4",
    "positiveCoordinates": true
  },
  {
    "visible": true,
    "validSize": true,
    "x": 20,
    "y": 1317,
    "width": 220,
    "height": 140,
    "left": 20,
    "top": 1317,
    "right": 240,
    "bottom": 1457,
    "minX": 20,
    "maxX": 240,
    "minY": 1317,
    "maxY": 1457,
    "xpath": "/HTML/BODY/DIV[5]/DIV/DIV/UL",
    "positiveCoordinates": true
  },
  {
    "visible": true,
    "validSize": true,
    "x": 30,
    "y": 1327,
    "width": 200,
    "height": 18,
    "left": 30,
    "top": 1327,
    "right": 230,
    "bottom": 1345,
    "minX": 30,
    "maxX": 230,
    "minY": 1327,
    "maxY": 1345,
    "xpath": "/HTML/BODY/DIV[5]/DIV/DIV/UL/LI",
    "positiveCoordinates": true
  },
  {
    "visible": true,
    "validSize": true,
    "x": 30,
    "y": 1327,
    "width": 200,
    "height": 18,
    "left": 30,
    "top": 1327,
    "right": 230,
    "bottom": 1345,
    "minX": 30,
    "maxX": 230,
    "minY": 1327,
    "maxY": 1345,
    "xpath": "/HTML/BODY/DIV[5]/DIV/DIV/UL/LI/A",
    "positiveCoordinates": true
  },
  {
    "visible": true,
    "validSize": true,
    "x": 30,
    "y": 1357,
    "width": 200,
    "height": 18,
    "left": 30,
    "top": 1357,
    "right": 230,
    "bottom": 1375,
    "minX": 30,
    "maxX": 230,
    "minY": 1357,
    "maxY": 1375,
    "xpath": "/HTML/BODY/DIV[5]/DIV/DIV/UL/LI[2]/A",
    "positiveCoordinates": true
  },
  {
    "visible": true,
    "validSize": true,
    "x": 30,
    "y": 1387,
    "width": 200,
    "height": 18,
    "left": 30,
    "top": 1387,
    "right": 230,
    "bottom": 1405,
    "minX": 30,
    "maxX": 230,
    "minY": 1387,
    "maxY": 1405,
    "xpath": "/HTML/BODY/DIV[5]/DIV/DIV/UL/LI[3]/A",
    "positiveCoordinates": true
  },
  {
    "visible": true,
    "validSize": true,
    "x": 30,
    "y": 1417,
    "width": 200,
    "height": 18,
    "left": 30,
    "top": 1417,
    "right": 230,
    "bottom": 1435,
    "minX": 30,
    "maxX": 230,
    "minY": 1417,
    "maxY": 1435,
    "xpath": "/HTML/BODY/DIV[5]/DIV/DIV/UL/LI[4]/A",
    "positiveCoordinates": true
  },
  {
    "visible": true,
    "validSize": true,
    "x": 0,
    "y": 1487,
    "width": 980,
    "height": 131,
    "left": 0,
    "top": 1487,
    "right": 980,
    "bottom": 1618,
    "minX": 0,
    "maxX": 980,
    "minY": 1487,
    "maxY": 1618,
    "xpath": "/HTML/BODY/DIV[6]",
    "positiveCoordinates": true
  },
  {
    "visible": true,
    "validSize": true,
    "x": 0,
    "y": 1509,
    "width": 980,
    "height": 60,
    "left": 0,
    "top": 1509,
    "right": 980,
    "bottom": 1569,
    "minX": 0,
    "maxX": 980,
    "minY": 1509,
    "maxY": 1569,
    "xpath": "/HTML/BODY/DIV[6]/DIV",
    "positiveCoordinates": true
  },
  {
    "visible": true,
    "validSize": true,
    "x": 367.6875,
    "y": 1509,
    "width": 58,
    "height": 48,
    "left": 367.6875,
    "top": 1509,
    "right": 425.6875,
    "bottom": 1557,
    "minX": 367.6875,
    "maxX": 425.6875,
    "minY": 1509,
    "maxY": 1557,
    "xpath": "/HTML/BODY/DIV[6]/DIV/SPAN",
    "positiveCoordinates": true
  },
  {
    "visible": true,
    "validSize": true,
    "x": 0,
    "y": 1579,
    "width": 980,
    "height": 19,
    "left": 0,
    "top": 1579,
    "right": 980,
    "bottom": 1598,
    "minX": 0,
    "maxX": 980,
    "minY": 1579,
    "maxY": 1598,
    "xpath": "/HTML/BODY/DIV[6]/DIV[2]",
    "positiveCoordinates": true
  },
  {
    "visible": true,
    "validSize": true,
    "x": 372.6875,
    "y": 1509,
    "width": 48,
    "height": 48,
    "left": 372.6875,
    "top": 1509,
    "right": 420.6875,
    "bottom": 1557,
    "minX": 372.6875,
    "maxX": 420.6875,
    "minY": 1509,
    "maxY": 1557,
    "xpath": "/HTML/BODY/DIV[6]/DIV/SPAN/A",
    "positiveCoordinates": true
  },
  {
    "visible": true,
    "validSize": true,
    "x": 434.890625,
    "y": 1509,
    "width": 48,
    "height": 48,
    "left": 434.890625,
    "top": 1509,
    "right": 482.890625,
    "bottom": 1557,
    "minX": 434.890625,
    "maxX": 482.890625,
    "minY": 1509,
    "maxY": 1557,
    "xpath": "/HTML/BODY/DIV[6]/DIV/SPAN[2]/A",
    "positiveCoordinates": true
  },
  {
    "visible": true,
    "validSize": true,
    "x": 497.09375,
    "y": 1509,
    "width": 48,
    "height": 48,
    "left": 497.09375,
    "top": 1509,
    "right": 545.09375,
    "bottom": 1557,
    "minX": 497.09375,
    "maxX": 545.09375,
    "minY": 1509,
    "maxY": 1557,
    "xpath": "/HTML/BODY/DIV[6]/DIV/SPAN[3]/A",
    "positiveCoordinates": true
  },
  {
    "visible": true,
    "validSize": true,
    "x": 559.296875,
    "y": 1509,
    "width": 48,
    "height": 48,
    "left": 559.296875,
    "top": 1509,
    "right": 607.296875,
    "bottom": 1557,
    "minX": 559.296875,
    "maxX": 607.296875,
    "minY": 1509,
    "maxY": 1557,
    "xpath": "/HTML/BODY/DIV[6]/DIV/SPAN[4]/A",
    "positiveCoordinates": true
  },
  {
    "visible": true,
    "validSize": true,
    "x": 0,
    "y": 1252,
    "width": 980,
    "height": 235,
    "left": 0,
    "top": 1252,
    "right": 980,
    "bottom": 1487,
    "minX": 0,
    "maxX": 980,
    "minY": 1252,
    "maxY": 1487,
    "xpath": "/HTML/BODY/DIV[5]",
    "positiveCoordinates": true
  },
  {
    "visible": true,
    "validSize": true,
    "x": 10,
    "y": 1273,
    "width": 960,
    "height": 214,
    "left": 10,
    "top": 1273,
    "right": 970,
    "bottom": 1487,
    "minX": 10,
    "maxX": 970,
    "minY": 1273,
    "maxY": 1487,
    "xpath": "/HTML/BODY/DIV[5]/DIV",
    "positiveCoordinates": true
  },
  {
    "visible": true,
    "validSize": true,
    "x": 20,
    "y": 1062,
    "width": 220,
    "height": 86,
    "left": 20,
    "top": 1062,
    "right": 240,
    "bottom": 1148,
    "minX": 20,
    "maxX": 240,
    "minY": 1062,
    "maxY": 1148,
    "xpath": "/HTML/BODY/DIV[4]/DIV[3]/DIV/DIV[2]/DIV",
    "positiveCoordinates": true
  },
  {
    "visible": true,
    "validSize": true,
    "x": 20,
    "y": 1062,
    "width": 220,
    "height": 86,
    "left": 20,
    "top": 1062,
    "right": 240,
    "bottom": 1148,
    "minX": 20,
    "maxX": 240,
    "minY": 1062,
    "maxY": 1148,
    "xpath": "/HTML/BODY/DIV[4]/DIV[3]/DIV/DIV[2]/DIV/DIV",
    "positiveCoordinates": true
  },
  {
    "visible": true,
    "validSize": true,
    "x": 260,
    "y": 1062,
    "width": 220,
    "height": 100,
    "left": 260,
    "top": 1062,
    "right": 480,
    "bottom": 1162,
    "minX": 260,
    "maxX": 480,
    "minY": 1062,
    "maxY": 1162,
    "xpath": "/HTML/BODY/DIV[4]/DIV[3]/DIV/DIV[2]/DIV[2]",
    "positiveCoordinates": true
  },
  {
    "visible": true,
    "validSize": true,
    "x": 260,
    "y": 1062,
    "width": 220,
    "height": 100,
    "left": 260,
    "top": 1062,
    "right": 480,
    "bottom": 1162,
    "minX": 260,
    "maxX": 480,
    "minY": 1062,
    "maxY": 1162,
    "xpath": "/HTML/BODY/DIV[4]/DIV[3]/DIV/DIV[2]/DIV[2]/DIV",
    "positiveCoordinates": true
  },
  {
    "visible": true,
    "validSize": true,
    "x": 140,
    "y": 714,
    "width": 340,
    "height": 186,
    "left": 140,
    "top": 714,
    "right": 480,
    "bottom": 900,
    "minX": 140,
    "maxX": 480,
    "minY": 714,
    "maxY": 900,
    "xpath": "/HTML/BODY/DIV[4]/DIV[2]/DIV/DIV[2]/DIV[2]",
    "positiveCoordinates": true
  },
  {
    "visible": true,
    "validSize": true,
    "x": 140,
    "y": 714,
    "width": 340,
    "height": 186,
    "left": 140,
    "top": 714,
    "right": 480,
    "bottom": 900,
    "minX": 140,
    "maxX": 480,
    "minY": 714,
    "maxY": 900,
    "xpath": "/HTML/BODY/DIV[4]/DIV[2]/DIV/DIV[2]/DIV[2]/UL",
    "positiveCoordinates": true
  },
  {
    "visible": true,
    "validSize": true,
    "x": 140,
    "y": 714,
    "width": 310,
    "height": 62,
    "left": 140,
    "top": 714,
    "right": 450,
    "bottom": 776,
    "minX": 140,
    "maxX": 450,
    "minY": 714,
    "maxY": 776,
    "xpath": "/HTML/BODY/DIV[4]/DIV[2]/DIV/DIV[2]/DIV[2]/UL/LI",
    "positiveCoordinates": true
  },
  {
    "visible": true,
    "validSize": true,
    "x": 140,
    "y": 776,
    "width": 310,
    "height": 62,
    "left": 140,
    "top": 776,
    "right": 450,
    "bottom": 838,
    "minX": 140,
    "maxX": 450,
    "minY": 776,
    "maxY": 838,
    "xpath": "/HTML/BODY/DIV[4]/DIV[2]/DIV/DIV[2]/DIV[2]/UL/LI[2]",
    "positiveCoordinates": true
  },
  {
    "visible": true,
    "validSize": true,
    "x": 140,
    "y": 838,
    "width": 310,
    "height": 62,
    "left": 140,
    "top": 838,
    "right": 450,
    "bottom": 900,
    "minX": 140,
    "maxX": 450,
    "minY": 838,
    "maxY": 900,
    "xpath": "/HTML/BODY/DIV[4]/DIV[2]/DIV/DIV[2]/DIV[2]/UL/LI[3]",
    "positiveCoordinates": true
  },
  {
    "visible": true,
    "validSize": true,
    "x": 10,
    "y": 617,
    "width": 960,
    "height": 283,
    "left": 10,
    "top": 617,
    "right": 970,
    "bottom": 900,
    "minX": 10,
    "maxX": 970,
    "minY": 617,
    "maxY": 900,
    "xpath": "/HTML/BODY/DIV[4]/DIV[2]/DIV/DIV[2]",
    "positiveCoordinates": true
  },
  {
    "visible": true,
    "validSize": true,
    "x": 20,
    "y": 617,
    "width": 940,
    "height": 97,
    "left": 20,
    "top": 617,
    "right": 960,
    "bottom": 714,
    "minX": 20,
    "maxX": 960,
    "minY": 617,
    "maxY": 714,
    "xpath": "/HTML/BODY/DIV[4]/DIV[2]/DIV/DIV",
    "positiveCoordinates": true
  },
  {
    "visible": true,
    "validSize": true,
    "x": 20,
    "y": 617,
    "width": 940,
    "height": 67,
    "left": 20,
    "top": 617,
    "right": 960,
    "bottom": 684,
    "minX": 20,
    "maxX": 960,
    "minY": 617,
    "maxY": 684,
    "xpath": "/HTML/BODY/DIV[4]/DIV[2]/DIV/DIV/H2",
    "positiveCoordinates": true
  },
  {
    "visible": true,
    "validSize": true,
    "x": 20,
    "y": 714,
    "width": 100,
    "height": 19,
    "left": 20,
    "top": 714,
    "right": 120,
    "bottom": 733,
    "minX": 20,
    "maxX": 120,
    "minY": 714,
    "maxY": 733,
    "xpath": "/HTML/BODY/DIV[4]/DIV[2]/DIV/DIV[2]/DIV",
    "positiveCoordinates": true
  },
  {
    "visible": true,
    "validSize": true,
    "x": 10,
    "y": 103,
    "width": 960,
    "height": 473,
    "left": 10,
    "top": 103,
    "right": 970,
    "bottom": 576,
    "minX": 10,
    "maxX": 970,
    "minY": 103,
    "maxY": 576,
    "xpath": "/HTML/BODY/DIV[4]/DIV/DIV",
    "positiveCoordinates": true
  },
  {
    "visible": true,
    "validSize": true,
    "x": 10,
    "y": 103,
    "width": 960,
    "height": 453,
    "left": 10,
    "top": 103,
    "right": 970,
    "bottom": 556,
    "minX": 10,
    "maxX": 970,
    "minY": 103,
    "maxY": 556,
    "xpath": "/HTML/BODY/DIV[4]/DIV/DIV/DIV",
    "positiveCoordinates": true
  },
  {
    "visible": true,
    "validSize": true,
    "x": 20,
    "y": 103,
    "width": 460,
    "height": 453,
    "left": 20,
    "top": 103,
    "right": 480,
    "bottom": 556,
    "minX": 20,
    "maxX": 480,
    "minY": 103,
    "maxY": 556,
    "xpath": "/HTML/BODY/DIV[4]/DIV/DIV/DIV/DIV",
    "positiveCoordinates": true
  },
  {
    "visible": true,
    "validSize": true,
    "x": 20,
    "y": 123,
    "width": 460,
    "height": 413,
    "left": 20,
    "top": 123,
    "right": 480,
    "bottom": 536,
    "minX": 20,
    "maxX": 480,
    "minY": 123,
    "maxY": 536,
    "xpath": "/HTML/BODY/DIV[4]/DIV/DIV/DIV/DIV/DIV",
    "positiveCoordinates": true
  },
  {
    "visible": true,
    "validSize": true,
    "x": 20,
    "y": 465,
    "width": 460,
    "height": 19,
    "left": 20,
    "top": 465,
    "right": 480,
    "bottom": 484,
    "minX": 20,
    "maxX": 480,
    "minY": 465,
    "maxY": 484,
    "xpath": "/HTML/BODY/DIV[4]/DIV/DIV/DIV/DIV/DIV/DIV",
    "positiveCoordinates": true
  },
  {
    "visible": true,
    "validSize": true,
    "x": 20,
    "y": 525,
    "width": 460,
    "height": 11,
    "left": 20,
    "top": 525,
    "right": 480,
    "bottom": 536,
    "minX": 20,
    "maxX": 480,
    "minY": 525,
    "maxY": 536,
    "xpath": "/HTML/BODY/DIV[4]/DIV/DIV/DIV/DIV/DIV/DIV[2]",
    "positiveCoordinates": true
  },
  {
    "visible": true,
    "validSize": true,
    "x": 10,
    "y": 0,
    "width": 960,
    "height": 50,
    "left": 10,
    "top": 0,
    "right": 970,
    "bottom": 50,
    "minX": 10,
    "maxX": 970,
    "minY": 0,
    "maxY": 50,
    "xpath": "/HTML/BODY/DIV[3]/DIV",
    "positiveCoordinates": true
  },
  {
    "visible": true,
    "validSize": true,
    "x": 10,
    "y": 0,
    "width": 188,
    "height": 50,
    "left": 10,
    "top": 0,
    "right": 198,
    "bottom": 50,
    "minX": 10,
    "maxX": 198,
    "minY": 0,
    "maxY": 50,
    "xpath": "/HTML/BODY/DIV[3]/DIV/DIV",
    "positiveCoordinates": true
  },
  {
    "visible": true,
    "validSize": true,
    "x": 352,
    "y": 0,
    "width": 618,
    "height": 50,
    "left": 352,
    "top": 0,
    "right": 970,
    "bottom": 50,
    "minX": 352,
    "maxX": 970,
    "minY": 0,
    "maxY": 50,
    "xpath": "/HTML/BODY/DIV[3]/DIV/DIV[2]",
    "positiveCoordinates": true
  },
  {
    "visible": true,
    "validSize": true,
    "x": 13,
    "y": 6,
    "width": 182,
    "height": 38,
    "left": 13,
    "top": 6,
    "right": 195,
    "bottom": 44,
    "minX": 13,
    "maxX": 195,
    "minY": 6,
    "maxY": 44,
    "xpath": "/HTML/BODY/DIV[3]/DIV/DIV/A",
    "positiveCoordinates": true
  },
  {
    "visible": true,
    "validSize": true,
    "x": 0,
    "y": 991,
    "width": 980,
    "height": 171,
    "left": 0,
    "top": 991,
    "right": 980,
    "bottom": 1162,
    "minX": 0,
    "maxX": 980,
    "minY": 991,
    "maxY": 1162,
    "xpath": "/HTML/BODY/DIV[4]/DIV[3]",
    "positiveCoordinates": true
  },
  {
    "visible": true,
    "validSize": true,
    "x": 0,
    "y": 991,
    "width": 980,
    "height": 171,
    "left": 0,
    "top": 991,
    "right": 980,
    "bottom": 1162,
    "minX": 0,
    "maxX": 980,
    "minY": 991,
    "maxY": 1162,
    "xpath": "/HTML/BODY/DIV[4]/DIV[3]/DIV",
    "positiveCoordinates": true
  },
  {
    "visible": true,
    "validSize": true,
    "x": 0,
    "y": 1018,
    "width": 980,
    "height": 20,
    "left": 0,
    "top": 1018,
    "right": 980,
    "bottom": 1038,
    "minX": 0,
    "maxX": 980,
    "minY": 1018,
    "maxY": 1038,
    "xpath": "/HTML/BODY/DIV[4]/DIV[3]/DIV/DIV",
    "positiveCoordinates": true
  },
  {
    "visible": true,
    "validSize": true,
    "x": 10,
    "y": 1062,
    "width": 960,
    "height": 100,
    "left": 10,
    "top": 1062,
    "right": 970,
    "bottom": 1162,
    "minX": 10,
    "maxX": 970,
    "minY": 1062,
    "maxY": 1162,
    "xpath": "/HTML/BODY/DIV[4]/DIV[3]/DIV/DIV[2]",
    "positiveCoordinates": true
  },
  {
    "visible": true,
    "validSize": true,
    "x": 0,
    "y": 0,
    "width": 980,
    "height": 1618,
    "left": 0,
    "top": 0,
    "right": 980,
    "bottom": 1618,
    "minX": 0,
    "maxX": 980,
    "minY": 0,
    "maxY": 1618,
    "xpath": "/HTML/BODY",
    "positiveCoordinates": true
  },
  {
    "visible": true,
    "validSize": true,
    "x": 0,
    "y": 0,
    "width": 980,
    "height": 53,
    "left": 0,
    "top": 0,
    "right": 980,
    "bottom": 53,
    "minX": 0,
    "maxX": 980,
    "minY": 0,
    "maxY": 53,
    "xpath": "/HTML/BODY/DIV[3]",
    "positiveCoordinates": true
  },
  {
    "visible": true,
    "validSize": true,
    "x": 0,
    "y": 53,
    "width": 980,
    "height": 1199,
    "left": 0,
    "top": 53,
    "right": 980,
    "bottom": 1252,
    "minX": 0,
    "maxX": 980,
    "minY": 53,
    "maxY": 1252,
    "xpath": "/HTML/BODY/DIV[4]",
    "positiveCoordinates": true
  },
  {
    "visible": true,
    "validSize": true,
    "x": 0,
    "y": 93,
    "width": 980,
    "height": 483,
    "left": 0,
    "top": 93,
    "right": 980,
    "bottom": 576,
    "minX": 0,
    "maxX": 980,
    "minY": 93,
    "maxY": 576,
    "xpath": "/HTML/BODY/DIV[4]/DIV",
    "positiveCoordinates": true
  },
  {
    "visible": true,
    "validSize": true,
    "x": 0,
    "y": 616,
    "width": 980,
    "height": 335,
    "left": 0,
    "top": 616,
    "right": 980,
    "bottom": 951,
    "minX": 0,
    "maxX": 980,
    "minY": 616,
    "maxY": 951,
    "xpath": "/HTML/BODY/DIV[4]/DIV[2]",
    "positiveCoordinates": true
  },
  {
    "visible": true,
    "validSize": true,
    "x": 9,
    "y": 616,
    "width": 962,
    "height": 335,
    "left": 9,
    "top": 616,
    "right": 971,
    "bottom": 951,
    "minX": 9,
    "maxX": 971,
    "minY": 616,
    "maxY": 951,
    "xpath": "/HTML/BODY/DIV[4]/DIV[2]/DIV",
    "positiveCoordinates": true
  }
]