[
  {
    "visible": true,
    "validSize": true,
    "x": 10,
    "y": 61.59375,
    "width": 468,
    "height": 153.90625,
    "left": 10,
    "top": 61.59375,
    "right": 478,
    "bottom": 215.5,
    "minX": 10,
    "maxX": 478,
    "minY": 61.59375,
    "maxY": 215.5,
    "xpath": "/HTML/BODY/HEADER/DIV/DIV",
    "positiveCoordinates": true
  },
  {
    "visible": true,
    "validSize": true,
    "x": 194,
    "y": 61.59375,
    "width": 100,
    "height": 87.90625,
    "left": 194,
    "top": 61.59375,
    "right": 294,
    "bottom": 149.5,
    "minX": 194,
    "maxX": 294,
    "minY": 61.59375,
    "maxY": 149.5,
    "xpath": "/HTML/BODY/HEADER/DIV/DIV/IMG",
    "positiveCoordinates": true
  },
  {
    "visible": true,
    "validSize": true,
    "x": 10,
    "y": 149.5,
    "width": 468,
    "height": 48,
    "left": 10,
    "top": 149.5,
    "right": 478,
    "bottom": 197.5,
    "minX": 10,
    "maxX": 478,
    "minY": 149.5,
    "maxY": 197.5,
    "xpath": "/HTML/BODY/HEADER/DIV/DIV/H1",
    "positiveCoordinates": true
  },
  {
    "visible": true,
    "validSize": true,
    "x": 10,
    "y": 197.5,
    "width": 468,
    "height": 18,
    "left": 10,
    "top": 197.5,
    "right": 478,
    "bottom": 215.5,
    "minX": 10,
    "maxX": 478,
    "minY": 197.5,
    "maxY": 215.5,
    "xpath": "/HTML/BODY/HEADER/DIV/DIV/H3",
    "positiveCoordinates": true
  },
  {
    "visible": true,
    "validSize": true,
    "x": 10,
    "y": 2338.09375,
    "width": 468,
    "height": 96,
    "left": 10,
    "top": 2338.09375,
    "right": 478,
    "bottom": 2434.09375,
    "minX": 10,
    "maxX": 478,
    "minY": 2338.09375,
    "maxY": 2434.09375,
    "xpath": "/HTML/BODY/DIV[2]/DIV/DIV[3]/P[15]",
    "positiveCoordinates": true
  },
  {
    "visible": true,
    "validSize": true,
    "x": 50,
    "y": 2450.09375,
    "width": 388,
    "height": 83.796875,
    "left": 50,
    "top": 2450.09375,
    "right": 438,
    "bottom": 2533.890625,
    "minX": 50,
    "maxX": 438,
    "minY": 2450.09375,
    "maxY": 2533.890625,
    "xpath": "/HTML/BODY/DIV[2]/DIV/DIV[3]/FIGURE[4]",
    "positiveCoordinates": true
  },
  {
    "visible": true,
    "validSize": true,
    "x": 10,
    "y": 2567.484375,
    "width": 468,
    "height": 36,
    "left": 10,
    "top": 2567.484375,
    "right": 478,
    "bottom": 2603.484375,
    "minX": 10,
    "maxX": 478,
    "minY": 2567.484375,
    "maxY": 2603.484375,
    "xpath": "/HTML/BODY/DIV[2]/DIV/DIV[3]/H2[3]",
    "positiveCoordinates": true
  },
  {
    "visible": true,
    "validSize": true,
    "x": 10,
    "y": 2622.671875,
    "width": 468,
    "height": 24,
    "left": 10,
    "top": 2622.671875,
    "right": 478,
    "bottom": 2646.671875,
    "minX": 10,
    "maxX": 478,
    "minY": 2622.671875,
    "maxY": 2646.671875,
    "xpath": "/HTML/BODY/DIV[2]/DIV/DIV[3]/P[16]",
    "positiveCoordinates": true
  },
  {
    "visible": true,
    "validSize": true,
    "x": 50,
    "y": 2450.09375,
    "width": 388,
    "height": 83.796875,
    "left": 50,
    "top": 2450.09375,
    "right": 438,
    "bottom": 2533.890625,
    "minX": 50,
    "maxX": 438,
    "minY": 2450.09375,
    "maxY": 2533.890625,
    "xpath": "/HTML/BODY/DIV[2]/DIV/DIV[3]/FIGURE[4]/PRE",
    "positiveCoordinates": true
  },
  {
    "visible": true,
    "validSize": true,
    "x": 10,
    "y": 2096.546875,
    "width": 468,
    "height": 38.390625,
    "left": 10,
    "top": 2096.546875,
    "right": 478,
    "bottom": 2134.9375,
    "minX": 10,
    "maxX": 478,
    "minY": 2096.546875,
    "maxY": 2134.9375,
    "xpath": "/HTML/BODY/DIV[2]/DIV/DIV[3]/H3[3]",
    "positiveCoordinates": true
  },
  {
    "visible": true,
    "validSize": true,
    "x": 10,
    "y": 2155.40625,
    "width": 468,
    "height": 24,
    "left": 10,
    "top": 2155.40625,
    "right": 478,
    "bottom": 2179.40625,
    "minX": 10,
    "maxX": 478,
    "minY": 2155.40625,
    "maxY": 2179.40625,
    "xpath": "/HTML/BODY/DIV[2]/DIV/DIV[3]/P[13]",
    "positiveCoordinates": true
  },
  {
    "visible": true,
    "validSize": true,
    "x": 10,
    "y": 2195.40625,
    "width": 468,
    "height": 48,
    "left": 10,
    "top": 2195.40625,
    "right": 478,
    "bottom": 2243.40625,
    "minX": 10,
    "maxX": 478,
    "minY": 2195.40625,
    "maxY": 2243.40625,
    "xpath": "/HTML/BODY/DIV[2]/DIV/DIV[3]/P[14]",
    "positiveCoordinates": true
  },
  {
    "visible": true,
    "validSize": true,
    "x": 10,
    "y": 2279.234375,
    "width": 468,
    "height": 38.390625,
    "left": 10,
    "top": 2279.234375,
    "right": 478,
    "bottom": 2317.625,
    "minX": 10,
    "maxX": 478,
    "minY": 2279.234375,
    "maxY": 2317.625,
    "xpath": "/HTML/BODY/DIV[2]/DIV/DIV[3]/H3[4]",
    "positiveCoordinates": true
  },
  {
    "visible": true,
    "validSize": true,
    "x": 10,
    "y": 1580.25,
    "width": 468,
    "height": 48,
    "left": 10,
    "top": 1580.25,
    "right": 478,
    "bottom": 1628.25,
    "minX": 10,
    "maxX": 478,
    "minY": 1580.25,
    "maxY": 1628.25,
    "xpath": "/HTML/BODY/DIV[2]/DIV/DIV[3]/P[11]",
    "positiveCoordinates": true
  },
  {
    "visible": true,
    "validSize": true,
    "x": 50,
    "y": 1644.25,
    "width": 388,
    "height": 273.78125,
    "left": 50,
    "top": 1644.25,
    "right": 438,
    "bottom": 1918.03125,
    "minX": 50,
    "maxX": 438,
    "minY": 1644.25,
    "maxY": 1918.03125,
    "xpath": "/HTML/BODY/DIV[2]/DIV/DIV[3]/FIGURE[3]",
    "positiveCoordinates": true
  },
  {
    "visible": true,
    "validSize": true,
    "x": 10,
    "y": 1953.859375,
    "width": 468,
    "height": 38.390625,
    "left": 10,
    "top": 1953.859375,
    "right": 478,
    "bottom": 1992.25,
    "minX": 10,
    "maxX": 478,
    "minY": 1953.859375,
    "maxY": 1992.25,
    "xpath": "/HTML/BODY/DIV[2]/DIV/DIV[3]/H3[2]",
    "positiveCoordinates": true
  },
  {
    "visible": true,
    "validSize": true,
    "x": 10,
    "y": 2012.71875,
    "width": 468,
    "height": 48,
    "left": 10,
    "top": 2012.71875,
    "right": 478,
    "bottom": 2060.71875,
    "minX": 10,
    "maxX": 478,
    "minY": 2012.71875,
    "maxY": 2060.71875,
    "xpath": "/HTML/BODY/DIV[2]/DIV/DIV[3]/P[12]",
    "positiveCoordinates": true
  },
  {
    "visible": true,
    "validSize": true,
    "x": 50,
    "y": 1644.25,
    "width": 388,
    "height": 273.78125,
    "left": 50,
    "top": 1644.25,
    "right": 438,
    "bottom": 1918.03125,
    "minX": 50,
    "maxX": 438,
    "minY": 1644.25,
    "maxY": 1918.03125,
    "xpath": "/HTML/BODY/DIV[2]/DIV/DIV[3]/FIGURE[3]/PRE",
    "positiveCoordinates": true
  },
  {
    "visible": true,
    "validSize": true,
    "x": 10,
    "y": 1327.984375,
    "width": 468,
    "height": 36,
    "left": 10,
    "top": 1327.984375,
    "right": 478,
    "bottom": 1363.984375,
    "minX": 10,
    "maxX": 478,
    "minY": 1327.984375,
    "maxY": 1363.984375,
    "xpath": "/HTML/BODY/DIV[2]/DIV/DIV[3]/H2[2]",
    "positiveCoordinates": true
  },
  {
    "visible": true,
    "validSize": true,
    "x": 10,
    "y": 1399.8125,
    "width": 468,
    "height": 38.390625,
    "left": 10,
    "top": 1399.8125,
    "right": 478,
    "bottom": 1438.203125,
    "minX": 10,
    "maxX": 478,
    "minY": 1399.8125,
    "maxY": 1438.203125,
    "xpath": "/HTML/BODY/DIV[2]/DIV/DIV[3]/H3",
    "positiveCoordinates": true
  },
  {
    "visible": true,
    "validSize": true,
    "x": 10,
    "y": 1458.671875,
    "width": 468,
    "height": 48,
    "left": 10,
    "top": 1458.671875,
    "right": 478,
    "bottom": 1506.671875,
    "minX": 10,
    "maxX": 478,
    "minY": 1458.671875,
    "maxY": 1506.671875,
    "xpath": "/HTML/BODY/DIV[2]/DIV/DIV[3]/P[10]",
    "positiveCoordinates": true
  },
  {
    "visible": true,
    "validSize": true,
    "x": 50,
    "y": 1522.671875,
    "width": 388,
    "height": 41.578125,
    "left": 50,
    "top": 1522.671875,
    "right": 438,
    "bottom": 1564.25,
    "minX": 50,
    "maxX": 438,
    "minY": 1522.671875,
    "maxY": 1564.25,
    "xpath": "/HTML/BODY/DIV[2]/DIV/DIV[3]/FIGURE[2]",
    "positiveCoordinates": true
  },
  {
    "visible": true,
    "validSize": true,
    "x": 50,
    "y": 1522.671875,
    "width": 388,
    "height": 41.578125,
    "left": 50,
    "top": 1522.671875,
    "right": 438,
    "bottom": 1564.25,
    "minX": 50,
    "maxX": 438,
    "minY": 1522.671875,
    "maxY": 1564.25,
    "xpath": "/HTML/BODY/DIV[2]/DIV/DIV[3]/FIGURE[2]/PRE",
    "positiveCoordinates": true
  },
  {
    "visible": true,
    "validSize": true,
    "x": 50,
    "y": 1108.8125,
    "width": 388,
    "height": 41.578125,
    "left": 50,
    "top": 1108.8125,
    "right": 438,
    "bottom": 1150.390625,
    "minX": 50,
    "maxX": 438,
    "minY": 1108.8125,
    "maxY": 1150.390625,
    "xpath": "/HTML/BODY/DIV[2]/DIV/DIV[3]/FIGURE",
    "positiveCoordinates": true
  },
  {
    "visible": true,
    "validSize": true,
    "x": 10,
    "y": 1166.390625,
    "width": 468,
    "height": 24,
    "left": 10,
    "top": 1166.390625,
    "right": 478,
    "bottom": 1190.390625,
    "minX": 10,
    "maxX": 478,
    "minY": 1166.390625,
    "maxY": 1190.390625,
    "xpath": "/HTML/BODY/DIV[2]/DIV/DIV[3]/P[7]",
    "positiveCoordinates": true
  },
  {
    "visible": true,
    "validSize": true,
    "x": 10,
    "y": 1206.390625,
    "width": 468,
    "height": 24,
    "left": 10,
    "top": 1206.390625,
    "right": 478,
    "bottom": 1230.390625,
    "minX": 10,
    "maxX": 478,
    "minY": 1206.390625,
    "maxY": 1230.390625,
    "xpath": "/HTML/BODY/DIV[2]/DIV/DIV[3]/P[8]",
    "positiveCoordinates": true
  },
  {
    "visible": true,
    "validSize": true,
    "x": 10,
    "y": 1246.390625,
    "width": 468,
    "height": 48,
    "left": 10,
    "top": 1246.390625,
    "right": 478,
    "bottom": 1294.390625,
    "minX": 10,
    "maxX": 478,
    "minY": 1246.390625,
    "maxY": 1294.390625,
    "xpath": "/HTML/BODY/DIV[2]/DIV/DIV[3]/P[9]",
    "positiveCoordinates": true
  },
  {
    "visible": true,
    "validSize": true,
    "x": 50,
    "y": 1108.8125,
    "width": 388,
    "height": 41.578125,
    "left": 50,
    "top": 1108.8125,
    "right": 438,
    "bottom": 1150.390625,
    "minX": 50,
    "maxX": 438,
    "minY": 1108.8125,
    "maxY": 1150.390625,
    "xpath": "/HTML/BODY/DIV[2]/DIV/DIV[3]/FIGURE/PRE",
    "positiveCoordinates": true
  },
  {
    "visible": true,
    "validSize": true,
    "x": 10,
    "y": 10,
    "width": 468,
    "height": 39.59375,
    "left": 10,
    "top": 10,
    "right": 478,
    "bottom": 49.59375,
    "minX": 10,
    "maxX": 478,
    "minY": 10,
    "maxY": 49.59375,
    "xpath": "/HTML/BODY/HEADER/DIV/UL",
    "positiveCoordinates": true
  },
  {
    "visible": true,
    "validSize": true,
    "x": 10,
    "y": 10,
    "width": 90,
    "height": 26.59375,
    "left": 10,
    "top": 10,
    "right": 100,
    "bottom": 36.59375,
    "minX": 10,
    "maxX": 100,
    "minY": 10,
    "maxY": 36.59375,
    "xpath": "/HTML/BODY/HEADER/DIV/UL/LI",
    "positiveCoordinates": true
  },
  {
    "visible": true,
    "validSize": true,
    "x": 10,
    "y": 10,
    "width": 90,
    "height": 26.59375,
    "left": 10,
    "top": 10,
    "right": 100,
    "bottom": 36.59375,
    "minX": 10,
    "maxX": 100,
    "minY": 10,
    "maxY": 36.59375,
    "xpath": "/HTML/BODY/HEADER/DIV/UL/LI/A",
    "positiveCoordinates": true
  },
  {
    "visible": true,
    "validSize": true,
    "x": 100,
    "y": 10,
    "width": 202.34375,
    "height": 26.59375,
    "left": 100,
    "top": 10,
    "right": 302.34375,
    "bottom": 36.59375,
    "minX": 100,
    "maxX": 302.34375,
    "minY": 10,
    "maxY": 36.59375,
    "xpath": "/HTML/BODY/HEADER/DIV/UL/LI[2]",
    "positiveCoordinates": true
  },
  {
    "visible": true,
    "validSize": true,
    "x": 302.34375,
    "y": 10,
    "width": 85.625,
    "height": 26.59375,
    "left": 302.34375,
    "top": 10,
    "right": 387.96875,
    "bottom": 36.59375,
    "minX": 302.34375,
    "maxX": 387.96875,
    "minY": 10,
    "maxY": 36.59375,
    "xpath": "/HTML/BODY/HEADER/DIV/UL/LI[3]",
    "positiveCoordinates": true
  },
  {
    "visible": true,
    "validSize": true,
    "x": 387.96875,
    "y": 10,
    "width": 90,
    "height": 26.59375,
    "left": 387.96875,
    "top": 10,
    "right": 477.96875,
    "bottom": 36.59375,
    "minX": 387.96875,
    "maxX": 477.96875,
    "minY": 10,
    "maxY": 36.59375,
    "xpath": "/HTML/BODY/HEADER/DIV/UL/LI[4]",
    "positiveCoordinates": true
  },
  {
    "visible": true,
    "validSize": true,
    "x": 100,
    "y": 10,
    "width": 202.34375,
    "height": 26.59375,
    "left": 100,
    "top": 10,
    "right": 302.34375,
    "bottom": 36.59375,
    "minX": 100,
    "maxX": 302.34375,
    "minY": 10,
    "maxY": 36.59375,
    "xpath": "/HTML/BODY/HEADER/DIV/UL/LI[2]/A",
    "positiveCoordinates": true
  },
  {
    "visible": true,
    "validSize": true,
    "x": 302.34375,
    "y": 10,
    "width": 85.625,
    "height": 26.59375,
    "left": 302.34375,
    "top": 10,
    "right": 387.96875,
    "bottom": 36.59375,
    "minX": 302.34375,
    "maxX": 387.96875,
    "minY": 10,
    "maxY": 36.59375,
    "xpath": "/HTML/BODY/HEADER/DIV/UL/LI[3]/A",
    "positiveCoordinates": true
  },
  {
    "visible": true,
    "validSize": true,
    "x": 387.96875,
    "y": 10,
    "width": 90,
    "height": 26.59375,
    "left": 387.96875,
    "top": 10,
    "right": 477.96875,
    "bottom": 36.59375,
    "minX": 387.96875,
    "maxX": 477.96875,
    "minY": 10,
    "maxY": 36.59375,
    "xpath": "/HTML/BODY/HEADER/DIV/UL/LI[4]/A",
    "positiveCoordinates": true
  },
  {
    "visible": true,
    "validSize": true,
    "x": 0,
    "y": 305.5,
    "width": 488,
    "height": 3015.578125,
    "left": 0,
    "top": 305.5,
    "right": 488,
    "bottom": 3321.078125,
    "minX": 0,
    "maxX": 488,
    "minY": 305.5,
    "maxY": 3321.078125,
    "xpath": "/HTML/BODY/DIV[2]",
    "positiveCoordinates": true
  },
  {
    "visible": true,
    "validSize": true,
    "x": 0,
    "y": 305.5,
    "width": 488,
    "height": 3015.578125,
    "left": 0,
    "top": 305.5,
    "right": 488,
    "bottom": 3321.078125,
    "minX": 0,
    "maxX": 488,
    "minY": 305.5,
    "maxY": 3321.078125,
    "xpath": "/HTML/BODY/DIV[2]/DIV",
    "positiveCoordinates": true
  },
  {
    "visible": true,
    "validSize": true,
    "x": 119,
    "y": 305.5,
    "width": 250,
    "height": 45,
    "left": 119,
    "top": 305.5,
    "right": 369,
    "bottom": 350.5,
    "minX": 119,
    "maxX": 369,
    "minY": 305.5,
    "maxY": 350.5,
    "xpath": "/HTML/BODY/DIV[2]/DIV/DIV",
    "positiveCoordinates": true
  },
  {
    "visible": true,
    "validSize": true,
    "x": 10,
    "y": 370.5,
    "width": 468,
    "height": 2950.578125,
    "left": 10,
    "top": 370.5,
    "right": 478,
    "bottom": 3321.078125,
    "minX": 10,
    "maxX": 478,
    "minY": 370.5,
    "maxY": 3321.078125,
    "xpath": "/HTML/BODY/DIV[2]/DIV/DIV[3]",
    "positiveCoordinates": true
  },
  {
    "visible": true,
    "validSize": true,
    "x": 10,
    "y": 1013.625,
    "width": 468,
    "height": 36,
    "left": 10,
    "top": 1013.625,
    "right": 478,
    "bottom": 1049.625,
    "minX": 10,
    "maxX": 478,
    "minY": 1013.625,
    "maxY": 1049.625,
    "xpath": "/HTML/BODY/DIV[2]/DIV/DIV[3]/H2",
    "positiveCoordinates": true
  },
  {
    "visible": true,
    "validSize": true,
    "x": 10,
    "y": 1068.8125,
    "width": 468,
    "height": 24,
    "left": 10,
    "top": 1068.8125,
    "right": 478,
    "bottom": 1092.8125,
    "minX": 10,
    "maxX": 478,
    "minY": 1068.8125,
    "maxY": 1092.8125,
    "xpath": "/HTML/BODY/DIV[2]/DIV/DIV[3]/P[6]",
    "positiveCoordinates": true
  },
  {
    "visible": true,
    "validSize": true,
    "x": 10,
    "y": 2686.671875,
    "width": 468,
    "height": 580.015625,
    "left": 10,
    "top": 2686.671875,
    "right": 478,
    "bottom": 3266.6875,
    "minX": 10,
    "maxX": 478,
    "minY": 2686.671875,
    "maxY": 3266.6875,
    "xpath": "/HTML/BODY/DIV[2]/DIV/DIV[3]/FOOTER",
    "positiveCoordinates": true
  },
  {
    "visible": true,
    "validSize": true,
    "x": 10,
    "y": 2712.0625,
    "width": 468,
    "height": 21.609375,
    "left": 10,
    "top": 2712.0625,
    "right": 478,
    "bottom": 2733.671875,
    "minX": 10,
    "maxX": 478,
    "minY": 2712.0625,
    "maxY": 2733.671875,
    "xpath": "/HTML/BODY/DIV[2]/DIV/DIV[3]/FOOTER/P",
    "positiveCoordinates": true
  },
  {
    "visible": true,
    "validSize": true,
    "x": 10,
    "y": 2748.0625,
    "width": 468,
    "height": 518.625,
    "left": 10,
    "top": 2748.0625,
    "right": 478,
    "bottom": 3266.6875,
    "minX": 10,
    "maxX": 478,
    "minY": 2748.0625,
    "maxY": 3266.6875,
    "xpath": "/HTML/BODY/DIV[2]/DIV/DIV[3]/FOOTER/P[2]",
    "positiveCoordinates": true
  },
  {
    "visible": true,
    "validSize": true,
    "x": 0,
    "y": 0,
    "width": 488,
    "height": 1000,
    "left": 0,
    "top": 0,
    "right": 488,
    "bottom": 1000,
    "minX": 0,
    "maxX": 488,
    "minY": 0,
    "maxY": 1000,
    "xpath": "/HTML/BODY",
    "positiveCoordinates": true
  },
  {
    "visible": true,
    "validSize": true,
    "x": 0,
    "y": 0,
    "width": 488,
    "height": 239.5,
    "left": 0,
    "top": 0,
    "right": 488,
    "bottom": 239.5,
    "minX": 0,
    "maxX": 488,
    "minY": 0,
    "maxY": 239.5,
    "xpath": "/HTML/BODY/HEADER",
    "positiveCoordinates": true
  },
  {
    "visible": true,
    "validSize": true,
    "x": 0,
    "y": 10,
    "width": 488,
    "height": 205.5,
    "left": 0,
    "top": 10,
    "right": 488,
    "bottom": 215.5,
    "minX": 0,
    "maxX": 488,
    "minY": 10,
    "maxY": 215.5,
    "xpath": "/HTML/BODY/HEADER/DIV",
    "positiveCoordinates": true
  },
  {
    "visible": true,
    "validSize": true,
    "x": 0,
    "y": 229.5,
    "width": 488,
    "height": 56,
    "left": 0,
    "top": 229.5,
    "right": 488,
    "bottom": 285.5,
    "minX": 0,
    "maxX": 488,
    "minY": 229.5,
    "maxY": 285.5,
    "xpath": "/HTML/BODY/DIV",
    "positiveCoordinates": true
  },
  {
    "visible": true,
    "validSize": true,
    "x": 10,
    "y": 370.5,
    "width": 468,
    "height": 127.9375,
    "left": 10,
    "top": 370.5,
    "right": 478,
    "bottom": 498.4375,
    "minX": 10,
    "maxX": 478,
    "minY": 370.5,
    "maxY": 498.4375,
    "xpath": "/HTML/BODY/DIV[2]/DIV/DIV[3]/P",
    "positiveCoordinates": true
  },
  {
    "visible": true,
    "validSize": true,
    "x": 10,
    "y": 524.03125,
    "width": 468,
    "height": 72,
    "left": 10,
    "top": 524.03125,
    "right": 478,
    "bottom": 596.03125,
    "minX": 10,
    "maxX": 478,
    "minY": 524.03125,
    "maxY": 596.03125,
    "xpath": "/HTML/BODY/DIV[2]/DIV/DIV[3]/P[2]",
    "positiveCoordinates": true
  },
  {
    "visible": true,
    "validSize": true,
    "x": 10,
    "y": 612.03125,
    "width": 468,
    "height": 96,
    "left": 10,
    "top": 612.03125,
    "right": 478,
    "bottom": 708.03125,
    "minX": 10,
    "maxX": 478,
    "minY": 612.03125,
    "maxY": 708.03125,
    "xpath": "/HTML/BODY/DIV[2]/DIV/DIV[3]/P[3]",
    "positiveCoordinates": true
  },
  {
    "visible": true,
    "validSize": true,
    "x": 10,
    "y": 724.03125,
    "width": 468,
    "height": 144,
    "left": 10,
    "top": 724.03125,
    "right": 478,
    "bottom": 868.03125,
    "minX": 10,
    "maxX": 478,
    "minY": 724.03125,
    "maxY": 868.03125,
    "xpath": "/HTML/BODY/DIV[2]/DIV/DIV[3]/P[4]",
    "positiveCoordinates": true
  },
  {
    "visible": true,
    "validSize": true,
    "x": 10,
    "y": 884.03125,
    "width": 468,
    "height": 96,
    "left": 10,
    "top": 884.03125,
    "right": 478,
    "bottom": 980.03125,
    "minX": 10,
    "maxX": 478,
    "minY": 884.03125,
    "maxY": 980.03125,
    "xpath": "/HTML/BODY/DIV[2]/DIV/DIV[3]/P[5]",
    "positiveCoordinates": true
  }
]